GridPolator-0.5.0.dist-info/METADATA
GridPolator-0.5.0.dist-info/WHEEL
GridPolator-0.5.0.dist-info/licenses/LICENSE
GridPolator/__init__.py
GridPolator/_gridpolator.cpython-313-x86_64-linux-gnu.so
GridPolator/astropy_units.py
GridPolator/binning.py
GridPolator/builtins/__init__.py
GridPolator/builtins/cache.py
GridPolator/builtins/phoenix_st.py
GridPolator/builtins/phoenix_vspec.py
GridPolator/config.py
GridPolator/grid.py
GridPolator-0.5.0.dist-info/RECORD
